cutiepy/__init__.py
cutiepy/__main__.py
cutiepy/__version__.py
cutiepy-0.1.0rc0.dist-info/METADATA
cutiepy-0.1.0rc0.dist-info/WHEEL
cutiepy-0.1.0rc0.dist-info/entry_points.txt
cutiepy-0.1.0rc0.dist-info/license_files/LICENSE
cutiepy-0.1.0rc0.dist-info/RECORD
